Workbook

Sheet Stakeholders
A1: Stakeholder ID | B1: Name/Group | C1: Role | D1: Interest | E1: Influence | F1: Key Concerns | G1: Source File(s) | H1: Supporting Quote/Evidence | I1: Evidence Status
A2: SH-01 | B2: Ingrid Solheim | C2: Founder, owner (daglig leder) and product owner | D2: Stop losing inquiries; self-service menus and booking; kitchen overview; deposit; keep Fiken; show food origin; live by 2027-03-01 | E2: High | F2: Lost inquiries (about 60 000 NOK); no-shows at weddings; budget about 450 000 NOK; deadline | G2: 01_Requirements/sources/01_interview_owner_2026-08-14.txt 00_Project_management/00_minutes_kickoff-meeting_2026-08-12.txt | H2: 01_interview_owner_2026-08-14.txt [header]: "Ingrid Solheim (founder and owner, Ekte Mat AS)" 00_minutes_kickoff-meeting_2026-08-12.txt [bullet 5]: "Ingrid acts as product owner; available Tuesdays 09-10" Note: Influence High: owner and appointed product owner (documented). | I2: DIRECT
A3: SH-02 | B3: Sunniva Berg | C3: Event coordinator | D3: One order record instead of Excel + printouts; capacity calendar; automatic 7-day reminders; allergy confirmation | E3: Medium | F3: Forgotten updates; slow replies in peak season; overbooking; corporate customers lost if deposit is forced | G3: 01_Requirements/sources/01_interview_event-coordinator_2026-08-15.txt | H3: 01_interview_event-coordinator_2026-08-15.txt [header]: "Sunniva Berg (event coordinator, Ekte Mat AS)" 01_interview_event-coordinator_2026-08-15.txt [Q3]: "If we force a deposit on them, we will lose them." Note: Influence Medium is an assessment: key daily user, no documented decision authority. | I3: ASSUMPTION
A4: SH-03 | B4: Mateo Rinaldi | C4: Head chef | D4: Kitchen wall-tablet overview; PIN login; edit seasonal menus; supplier-linked ingredients; prep list; offline access | E4: Medium | F4: Allergy visibility; speed; internet outages | G4: 01_Requirements/sources/01_interview_head-chef_2026-08-15.txt | H4: 01_interview_head-chef_2026-08-15.txt [header]: "Mateo Rinaldi (head chef)" 01_interview_head-chef_2026-08-15.txt [Q1]: "One screen in the kitchen. Tablet on the wall." Note: Influence Medium is an assessment: owns kitchen operations, no documented project authority. | I4: ASSUMPTION
A5: SH-04 | B5: Henrik Aas (Fjordtek AS) | C5: Office manager at Ekte Mat's biggest corporate customer | D5: Company login; standing orders; copy orders; change until 10:00 day before; approval above 15 000 NOK; monthly EHF invoice | E5: Medium | F5: Late confirmations; no prepayment allowed; EU/EEA data storage; deletion of employee names | G5: 01_Requirements/sources/01_interview_corporate-customer_2026-08-19.txt 01_Requirements/sources/01_interview_owner_2026-08-14.txt | H5: 01_interview_corporate-customer_2026-08-19.txt [header]: "Henrik Aas (office manager, Fjordtek AS - fictional company, 180 employees)" 01_interview_owner_2026-08-14.txt [Q6]: "maybe Fjordtek - they are our biggest corporate customer." Note: Influence Medium is an assessment based on 'biggest corporate customer'. | I5: ASSUMPTION
A6: SH-05 | B6: Fjordtek IT department | C6: IT function of a corporate customer (not interviewed) | D6: Data location and deletion | E6: Low | F6: Data stored in EU/EEA; employee names deleted at end of relationship | G6: 01_Requirements/sources/01_interview_corporate-customer_2026-08-19.txt | H6: 01_interview_corporate-customer_2026-08-19.txt [Q4]: "Our IT department will ask where our data is stored." Note: Group named only indirectly; influence assessed. | I6: ASSUMPTION
A7: SH-06 | B7: Fjordtek finance department | C7: Finance function of a corporate customer (not interviewed) | D7: Invoice-based payment | E7: Low | F7: Prepayment not allowed | G7: 01_Requirements/sources/01_interview_corporate-customer_2026-08-19.txt | H7: 01_interview_corporate-customer_2026-08-19.txt [Q3]: "We cannot prepay, our finance department does not allow it." Note: Group named only indirectly; influence assessed. | I7: ASSUMPTION
A8: SH-07 | B8: Corporate customers (group) | C8: Customer segment: weekly lunches and meetings | D8: Recurring orders, several orderers, EHF invoicing with references, English menus | E8: Medium | F8: PDF invoices rejected; repetitive weekly e-mails; reorder without details | G8: 00_Project_management/00_minutes_kickoff-meeting_2026-08-12.txt 04_Data/04_dataset_customer-emails_2026-10-20.csv | H8: 00_minutes_kickoff-meeting_2026-08-12.txt [bullet 3]: "Customer groups: corporate (weekly lunches, meetings), private (parties), weddings, health-conscious" 04_dataset_customer-emails_2026-10-20.csv [E004]: "our finance department only accepts EHF invoices with our PO number." 04_dataset_customer-emails_2026-10-20.csv [E007]: "It is a pain to e-mail every week." Note: Segment documented; influence assessed. | I8: ASSUMPTION
A9: SH-08 | B9: Private customers (parties) | C9: Customer segment: parties, birthdays, confirmations | D9: Vipps payment, e-mail receipt, pick-up option, phone ordering | E9: Low | F9: Payment method; ability to order without internet | G9: 00_Project_management/00_minutes_kickoff-meeting_2026-08-12.txt 04_Data/04_dataset_customer-emails_2026-10-20.csv | H9: 00_minutes_kickoff-meeting_2026-08-12.txt [bullet 3]: "private (parties)" 04_dataset_customer-emails_2026-10-20.csv [E009]: "Kan jeg betale med Vipps for bursdag 30 pers?" [translation: Can I pay with Vipps for a birthday party of 30?] 04_dataset_customer-emails_2026-10-20.csv [E024]: "Kan jeg fortsatt bestille på telefon?" [translation: Can I still order by phone?] Note: Segment documented; influence assessed. | I9: ASSUMPTION
A10: SH-09 | B10: Wedding customers | C10: Customer segment: weddings (season from May 2027) | D10: Capacity for served dinners; deposit amount | E10: Low | F10: Availability on the date; deposit terms | G10: 01_Requirements/sources/01_interview_owner_2026-08-14.txt 04_Data/04_dataset_customer-emails_2026-10-20.csv | H10: 01_interview_owner_2026-08-14.txt [Q2]: "We have had too many no-shows at weddings." 04_dataset_customer-emails_2026-10-20.csv [E005]: "Har dere kapasitet? Hvor mye må vi betale i depositum?" [translation: Do you have capacity? How much do we have to pay as a deposit?] Note: Segment documented; influence assessed. | I10: ASSUMPTION
A11: SH-10 | B11: Health-conscious customers | C11: Customer segment named at kick-off | D11: Not documented beyond the segment name | E11: Low | F11: Not documented (no interview or e-mail attributable) | G11: 00_Project_management/00_minutes_kickoff-meeting_2026-08-12.txt | H11: 00_minutes_kickoff-meeting_2026-08-12.txt [bullet 3]: "health-conscious" Note: Only the segment name is evidenced; concerns unknown. | I11: ASSUMPTION
A12: SH-11 | B12: Driver (name not documented) | C12: Delivers orders (not interviewed) | D12: Not documented | E12: Low | F12: Currently gets the address from a printout and uses own phone | G12: 02_Analysis_and_models/02_process_as-is-order-handling_2026-08-15.md 03_Architecture/03_landscape_current-it_2026-10-20.txt | H12: 02_process_as-is-order-handling_2026-08-15.md [step 10]: "Kitchen prepares, driver delivers. Driver gets the address from the printout." 03_landscape_current-it_2026-10-20.txt [Driver]: "Driver: own phone, Google Maps" Note: Role evidenced; needs not elicited (see issue register). | I12: ASSUMPTION
... A15: SH-14 | B15: Suppliers (farms, boats) | C15: Ingredient suppliers whose origin is shown | D15: Being shown as origin; becoming a supplier | E15: Low | F15: Not elicited | G15: 01_Requirements/sources/01_interview_owner_2026-08-14.txt 01_Requirements/sources/01_interview_head-chef_2026-08-15.txt 04_Data/04_dataset_customer-emails_2026-10-20.csv | H15: 01_interview_owner_2026-08-14.txt [Q4]: "where the lamb or the fish comes from - the farm, the boat." 01_interview_head-chef_2026-08-15.txt [Q2]: "ingredients should be linked to suppliers" 04_dataset_customer-emails_2026-10-20.csv [E025]: "we are an organic vegetable farm in Hardanger and would like to become a supplier." Note: Group evidenced; influence assessed. | I15: ASSUMPTION

Sheet User stories
A1: Story ID | B1: Epic ID | C1: Epic Name | D1: User Story | E1: Acceptance Criteria (2–3) | F1: MoSCoW Priority | G1: One-line Priority Rationale | H1: Source File(s) | I1: Supporting Quote | J1: Evidence Status | K1: Assumptions/Dependencies
A2: US-01 | B2: EP-01 | C2: Online menus and booking requests | D2: As a prospective customer, I want to see current menus and prices online at any time so that I can plan an event without e-mailing for a quote. | E2: AC1: Given a published menu, when a visitor opens the menu page, then each dish is shown with its price in NOK. AC2: Given it is outside office hours, 8.00 to 17.00, when a visitor opens the website, then menus and prices are available without contacting staff. | F2: Must | G2: Named by the owner as a first function; core of the documented project goal. | H2: 01_Requirements/sources/01_interview_owner_2026-08-14.txt 04_Data/04_dataset_customer-emails_2026-10-20.csv 01_Requirements/sources/01_vision_draft-v0.3_2026-10-20.docx | I2: 01_interview_owner_2026-08-14.txt [Q2]: "Customers must be able to see our menus and prices and send a booking request themselves, at any hour." 04_dataset_customer-emails_2026-10-20.csv [E001]: "Can you send the menu and price?" 04_dataset_customer-emails_2026-10-20.csv [E015]: "Can you send a price list PDF?" 01_vision_draft-v0.3_2026-10-20.docx [para 1]: "lets customers see menus, prices and food origin" | J2: DIRECT | K2: Pricing unit (per person, as in the autumn menu draft) assumed for all packages; VAT display and minimum order not documented.
A3: US-02 | B3: EP-01 | C3: Online menus and booking requests | D3: As a prospective customer, I want to send a booking request online at any hour so that my request is registered and not lost. | E3: AC1: Given a visitor has completed the booking form, when they submit it, then the request is stored and listed for the coordinator. AC2: Given the submission cannot be stored, when the visitor submits, then an error message is shown to the visitor. | F3: Must | G3: Lost inquiries are the main documented problem; replaces e-mail intake (kick-off goal). | H3: 01_Requirements/sources/01_interview_owner_2026-08-14.txt 00_Project_management/00_minutes_kickoff-meeting_2026-08-12.txt 04_Data/04_dataset_customer-emails_2026-10-20.csv | I3: 01_interview_owner_2026-08-14.txt [Q1]: "We lose inquiries. Last December we found three julebord requests in the spam folder after the date had passed." 00_minutes_kickoff-meeting_2026-08-12.txt [bullet 1]: "Goal: replace e-mail/phone/Excel ordering with an online ordering and event booking system" 04_dataset_customer-emails_2026-10-20.csv [E023]: "I tried the contact form on your website three times and got an error." 04_dataset_customer-emails_2026-10-20.csv [E006]: "We have booked another caterer now." | J3: DIRECT | K3: Required booking fields are not defined. Whether a request is auto-confirmed or reviewed by the coordinator is not decided.
A4: US-03 | B4: EP-01 | C4: Online menus and booking requests | D4: As a prospective customer, I want to see which dates are available so that I only request dates Ekte Mat can serve. | E4: AC1: Given a date has reached the capacity limit, when a customer views the availability calendar, then the date is shown as unavailable. AC2: Given a date has remaining capacity, when a customer views the calendar, then the date can be selected for a request. | F4: Should | G4: Clear customer need, but booking requests can be handled without it at go-live. | H4: 04_Data/04_dataset_customer-emails_2026-10-20.csv | I4: 04_dataset_customer-emails_2026-10-20.csv [E001]: "Is it possible to see online which dates are free?" 04_dataset_customer-emails_2026-10-20.csv [E005]: "Har dere kapasitet?" [translation: Do you have capacity?] | J4: DIRECT | K4: Depends on US-10 and the capacity rule (ISS-06). Whether exact remaining capacity is shown publicly is not decided.
A5: US-04 | B5: EP-01 | C5: Online menus and booking requests | D5: As a customer, I want an automatic confirmation and a visible status for my order so that I know whether it is accepted. | E5: AC1: Given a booking request is stored, when submission completes, then the customer receives a message that the request was received. AC2: Given the coordinator confirms the order, when the status changes, then the customer is notified that the order is confirmed. | F5: Should | G5: Strongly evidenced pain point, but not named as a go-live condition. | H5: 01_Requirements/sources/01_interview_corporate-customer_2026-08-19.txt 04_Data/04_dataset_customer-emails_2026-10-20.csv | I5: 01_interview_corporate-customer_2026-08-19.txt [Q1]: "Then I wait for a confirmation. Sometimes it arrives Monday morning, which is too late for me." 04_dataset_customer-emails_2026-10-20.csv [E011]: "Is our order for tomorrow confirmed? We never got a confirmation e-mail." | J5: DIRECT | K5: PO REVIEW: priority could be Must because it is closely tied to the lost-inquiry problem. Notification channel (e-mail) is an ASSUMPTION.
A6: US-05 | B6: EP-01 | C6: Online menus and booking requests | D6: As a customer, I want menus to show where key ingredients come from (farm or boat) so that I can choose food with a known origin. | E6: AC1: Given a dish has an ingredient linked to a supplier, when a customer views the menu, then the origin of that ingredient is shown. [Only one AC is supported by the evidence; further criteria need PO input.] | F6: Should | G6: Part of the vision and brand, but stated by the owner as a wish ('would love'). | H6: 01_Requirements/sources/01_interview_owner_2026-08-14.txt 04_Data/04_dataset_customer-emails_2026-10-20.csv 01_Requirements/sources/01_vision_draft-v0.3_2026-10-20.docx | I6: 01_interview_owner_2026-08-14.txt [Q4]: "I would love every menu to show where the lamb or the fish comes from - the farm, the boat." 04_dataset_customer-emails_2026-10-20.csv [E008]: "Which farm is the lamb from?" 01_vision_draft-v0.3_2026-10-20.docx [para 1]: "see menus, prices and food origin" | J6: DIRECT | K6: Depends on US-19. Which ingredients must show origin ('every menu' vs key ingredients) is not defined. Only one AC is supported by evidence.
A7: US-06 | B7: EP-01 | C7: Online menus and booking requests | D7: As a customer, I want the allergens in each dish to be clearly marked so that guests with allergies can choose safely. | E7: AC1: Given a dish contains an allergen on the labelling list, when the menu is displayed, then that allergen is shown for the dish. AC2: Given the English version of the menu, when it is displayed, then the same allergen markings are shown. | F7: Should | G7: Safety-relevant and requested; no source states it as a go-live condition. | H7: 04_Data/04_reference_lunch-menu-autumn_2026-10-20.txt 04_Data/04_dataset_customer-emails_2026-10-20.csv | I7: 04_reference_lunch-menu-autumn_2026-10-20.txt [last line]: "Allergens to be labelled: fish, milk, gluten, nuts, celery, mustard." 04_dataset_customer-emails_2026-10-20.csv [E012]: "Is your menu available in English with allergens marked?" 04_dataset_customer-emails_2026-10-20.csv [E019]: "Please label gluten-free items clearly on the buffet." | J7: DIRECT | K7: PO REVIEW: consider Must. Legal allergen-labelling obligations are not in the evidence. E019 concerns physical buffet labels, so applying it to the online menu is INFERRED. Depends on NFR-10.
A8: US-07 | B8: EP-01 | C8: Online menus and booking requests | D8: As a customer, I want to record allergies and diets per guest group in my order so that the kitchen can prepare safe meals. | E8: AC1: Given an order, when the customer adds a guest group, then they can enter the number of guests and their allergies or diets for that group. AC2: Given allergy information is entered, when the order is saved, then no guest name is required for the allergy data. | F8: Must | G8: Documented as mandatory for every order; safety incident in 2024; GDPR advice on health data. | H8: 01_Requirements/sources/01_interview_event-coordinator_2026-08-15.txt 01_Requirements/sources/01_note_gdpr-consultant_2026-08-20.txt 04_Data/04_dataset_customer-emails_2026-10-20.csv | I8: 01_interview_event-coordinator_2026-08-15.txt [Q5]: "Every order has to show allergies and diets per guest group" 01_note_gdpr-consultant_2026-08-20.txt [bullet 1]: "Store per guest group, not per named guest, unless strictly needed." 04_dataset_customer-emails_2026-10-20.csv [E002]: "To av gjestene har nøtteallergi og en er cøliaki." [translation: Two of the guests have a nut allergy and one has coeliac disease.] 04_dataset_customer-emails_2026-10-20.csv [E022]: "Adding one guest with shellfish allergy to the order for tonight." | J8: DIRECT | K8: Standard list of allergens/diets: the menu draft lists six allergens; whether the order form uses the same list is not decided.
A9: US-08 | B9: EP-01 | C9: Online menus and booking requests | D9: As a corporate customer, I want to see the share of local ingredients per order so that I can use it in sustainability (ESG) reporting. | E9: AC1: Given an order whose dishes have ingredients with recorded origin, when the customer views the order, then the share of local ingredients is shown. [Only one AC is supported by the evidence; further criteria need PO input.] | F9: Could | G9: Single customer request; not linked to go-live needs. | H9: 04_Data/04_dataset_customer-emails_2026-10-20.csv | I9: 04_dataset_customer-emails_2026-10-20.csv [E021]: "can you tell us the CO2 footprint or at least the share of local ingredients per order?" | J9: DIRECT | K9: Definition of 'local' and the calculation basis (weight, cost, count) are missing. Depends on US-19. CO2 footprint not included (no data source).
A10: US-09 | B10: EP-02 | C10: Order management and event coordination | D10: As the event coordinator, I want to register and manage all orders, including orders received by phone or e-mail, in one system so that I no longer keep Excel and printouts in sync. | E10: AC1: Given an order received by phone, when the coordinator registers it, then it appears in the same order list as online orders. AC2: Given the coordinator changes an order, when the change is saved, then the kitchen overview shows the updated order without re-printing. | F10: Must | G10: Replacing e-mail/phone/Excel ordering is the documented project goal. | H10: 01_Requirements/sources/01_interview_event-coordinator_2026-08-15.txt 02_Analysis_and_models/02_process_as-is-order-handling_2026-08-15.md 04_Data/04_dataset_customer-emails_2026-10-20.csv 01_Requirements/sources/01_vision_draft-v0.3_2026-10-20.docx | I10: 01_interview_event-coordinator_2026-08-15.txt [Q1]: "I have to remember to update both the sheet and the printout. Sometimes I forget." 02_process_as-is-order-handling_2026-08-15.md [step 1]: "Customer sends an e-mail or calls (phone calls are noted on paper)." 04_dataset_customer-emails_2026-10-20.csv [E024]: "Kan jeg fortsatt bestille på telefon?" [translation: Can I still order by phone?] 01_vision_draft-v0.3_2026-10-20.docx [para 1]: "it gives the kitchen one reliable overview of every order and allergy." | J10: DIRECT | K10: Assumes phone remains an order channel (ISS-12). Migration of existing Excel orders is not addressed.
A11: US-10 | B11: EP-02 | C11: Order management and event coordination | D11: As the event coordinator, I want a calendar showing booked guests per day against kitchen capacity so that I do not overbook. | E11: AC1: Given confirmed orders on a date, when the coordinator opens the calendar, then the total number of guests for that date is shown. AC2: Given the booked guests for a date exceed the capacity limit, when the calendar is shown, then the date is flagged as over capacity. | F11: Should | G11: Clear operational need; booking requests are still reviewed manually. | H11: 01_Requirements/sources/01_interview_event-coordinator_2026-08-15.txt 02_Analysis_and_models/02_process_as-is-order-handling_2026-08-15.md | I11: 01_interview_event-coordinator_2026-08-15.txt [Q4]: "A calendar that shows how many guests we already have per day, so I do not overbook. Our kitchen can do about 400 covers a day, 250 if there is a wedding with a served dinner." 02_process_as-is-order-handling_2026-08-15.md [step 3]: "If the day is "full" (gut feeling), she proposes another date." | J11: DIRECT | K11: PO REVIEW: becomes Must if online requests are confirmed automatically. Capacity values are approximate ('about'): see ISS-06.
A12: US-11 | B12: EP-02 | C12: Order management and event coordination | D12: As a customer, I want to change the number of guests and allergy information for my order online so that changes reach Ekte Mat without phone calls. | E12: AC1: Given an existing order before the change deadline, when the customer changes the number of guests, then the order shows the new number for the coordinator and the kitchen. AC2: Given a customer adds a guest group with an allergy, when the change is saved, then the kitchen overview shows the allergy for that order. | F12: Should | G12: Frequent pain point; not documented as a go-live condition. | H12: 01_Requirements/sources/01_interview_corporate-customer_2026-08-19.txt 04_Data/04_dataset_customer-emails_2026-10-20.csv 02_Analysis_and_models/02_process_as-is-order-handling_2026-08-15.md 01_Requirements/sources/01_vision_draft-v0.3_2026-10-20.docx | I12: 01_interview_corporate-customer_2026-08-19.txt [Q2]: "change the number of people until 10:00 the day before" 04_dataset_customer-emails_2026-10-20.csv [E003]: "we need to change from 40 to 55 guests for our event next Thursday. I called yesterday but nobody picked up." 02_process_as-is-order-handling_2026-08-15.md [step 8]: "Changes (guest count, allergies) arrive by phone/e-mail" 01_vision_draft-v0.3_2026-10-20.docx [para 1]: "book and change orders any time" | J12: DIRECT | K12: The change deadline is not agreed: 10:00 the day before is one customer's wish, while the vision says 'any time' (ISS-03).
... A32: US-31 | B32: EP-06 | C32: Privacy and data-subject rights | D32: As a customer, I want my personal data to be deleted when I ask, or when my company stops being a customer, so that my privacy is respected. | E32: AC1: Given a deletion request, when it is processed, then the customer's personal data is deleted except data that must be kept for bookkeeping, and the customer receives a confirmation. AC2: Given a corporate customer relationship ends, when the deletion process runs, then the names of that company's employees are deleted. | F32: Must | G32: Documented obligation in the GDPR advice and a corporate customer requirement. | H32: 01_Requirements/sources/01_note_gdpr-consultant_2026-08-20.txt 04_Data/04_dataset_customer-emails_2026-10-20.csv 01_Requirements/sources/01_interview_corporate-customer_2026-08-19.txt | I32: 01_note_gdpr-consultant_2026-08-20.txt [bullet 3]: "Customers must be able to request access and deletion." 01_note_gdpr-consultant_2026-08-20.txt [bullet 2]: "Keep order data needed for bookkeeping 5 years (Norwegian Bookkeeping Act)" 04_dataset_customer-emails_2026-10-20.csv [E010]: "Please delete all personal data you have about me and confirm by e-mail." 01_interview_corporate-customer_2026-08-19.txt [Q4]: "they want to know that you delete our employees' names when we stop being a customer." | J32: DIRECT | K32: Deletion deadlines are missing (NFR-08, ISS-07). E010 is a real pending request in the current process; it is outside the system scope but should be handled now.

Sheet Non-functional requirements
A1: Requirement ID | B1: Quality Characteristic | C1: Requirement Statement | D1: Metric | E1: Target Value | F1: Unit | G1: Measurement Conditions/Verification Method | H1: Source File(s) | I1: Supporting Quote | J1: Evidence Status | K1: Assumptions/Unresolved Details
A2: NFR-01 | B2: Performance efficiency (time behaviour) | C2: Customer-facing pages shall load fast enough not to deter customers. CANDIDATE: no target agreed. | D2: Page load time | E2: TBC (not agreed) | F2: s | G2: To be defined once a target and test conditions (device, network, page set) are agreed. | H2: 01_Requirements/sources/01_interview_head-chef_2026-08-15.txt | I2: 01_interview_head-chef_2026-08-15.txt [Q4]: "Please do not make it slow. The old booking plugin on the website took ten seconds to load a page." | J2: UNRESOLVED | K2: 10 s is the unacceptable baseline, not a target. Question in ISS-10.
A3: NFR-02 | B3: Availability | C3: Customers shall be able to view menus and send booking requests at any hour. CANDIDATE: availability target missing. | D3: Availability of menu and booking functions | E3: TBC (not agreed) | F3: % per month | G3: To be defined: measurement period, maintenance windows, monitoring method. | H3: 01_Requirements/sources/01_interview_owner_2026-08-14.txt | I3: 01_interview_owner_2026-08-14.txt [Q2]: "send a booking request themselves, at any hour." | J3: UNRESOLVED | K3: 'At any hour' gives no numeric target. Question in ISS-11.
A4: NFR-03 | B4: Reliability (fault tolerance) | C4: The kitchen view shall still show today's orders during an internet outage. | D4: Today's orders viewable on the kitchen device with the network disconnected | E4: All of today's orders as of the last successful update | F4: orders | G4: Test: load the kitchen view, disconnect the network, verify that all of today's orders remain visible. | H4: 01_Requirements/sources/01_interview_head-chef_2026-08-15.txt | I4: 01_interview_head-chef_2026-08-15.txt [Q3]: "It happened twice last winter. The kitchen must still see today's orders. Printing works too, but the screen should not just go blank." | J4: DIRECT | K4: Acceptable data age and whether changes are possible offline are not documented.
A5: NFR-04 | B5: Security / privacy (data residency) | C5: Personal data shall be stored and processed only in the EU/EEA. | D5: Share of personal data stored or processed in the EU/EEA | E5: 100 | F5: % | G5: Review of hosting locations and sub-processors listed in each provider's data processing agreement. | H5: 03_Architecture/03_landscape_current-it_2026-10-20.txt 01_Requirements/sources/01_interview_corporate-customer_2026-08-19.txt | I5: 03_landscape_current-it_2026-10-20.txt [Constraints]: "data must stay in EU/EEA (GDPR)" 01_interview_corporate-customer_2026-08-19.txt [Q4]: "They want it in the EU/EEA" | J5: DIRECT | K5: 100 % follows from 'must stay'. Not a claim of legal compliance.
A6: NFR-05 | B6: Privacy (data minimisation) | C6: Allergy and dietary information shall be stored per guest group, not per named guest, unless strictly needed. | D6: Data fields linking allergy or diet data to a named guest | E6: 0 (unless a documented exception exists) | F6: fields | G6: Data-model review before release. | H6: 01_Requirements/sources/01_note_gdpr-consultant_2026-08-20.txt | I6: 01_note_gdpr-consultant_2026-08-20.txt [bullet 1]: "Allergy and dietary information about named persons can be health data (special category, GDPR art. 9). Store per guest group, not per named guest, unless strictly needed." | J6: DIRECT | K6: Expressing this as a field count is an interpretation. 'Strictly needed' exceptions are undefined.
A7: NFR-06 | B7: Privacy (retention) | C7: Order data needed for bookkeeping shall be kept for 5 years. | D7: Retention period for bookkeeping order data | E7: 5 | F7: years | G7: Review of retention configuration; test that bookkeeping data survives a deletion request. | H7: 01_Requirements/sources/01_note_gdpr-consultant_2026-08-20.txt | I7: 01_note_gdpr-consultant_2026-08-20.txt [bullet 2]: "Keep order data needed for bookkeeping 5 years (Norwegian Bookkeeping Act)" | J7: DIRECT | K7: Based on a phone note from the consultant; not legally verified here. Start of the period and the exact fields are undefined.
A8: NFR-07 | B8: Privacy (retention) | C8: Personal data not needed for bookkeeping shall have a shorter retention period. CANDIDATE: period missing. | D8: Retention period for other personal data | E8: TBC (shorter than 5 years) | F8: months | G8: To be defined. | H8: 01_Requirements/sources/01_note_gdpr-consultant_2026-08-20.txt | I8: 01_note_gdpr-consultant_2026-08-20.txt [bullet 2]: "other personal data should have a shorter retention period." | J8: UNRESOLVED | K8: Retention period not stated. Question in ISS-07.
A9: NFR-08 | B9: Privacy (deletion) | C9: Employee names of a corporate customer shall be deleted when the customer relationship ends. CANDIDATE: deadline missing. | D9: Time from end of customer relationship to deletion | E9: TBC (not agreed) | F9: days | G9: To be defined. | H9: 01_Requirements/sources/01_interview_corporate-customer_2026-08-19.txt | I9: 01_interview_corporate-customer_2026-08-19.txt [Q4]: "they want to know that you delete our employees' names when we stop being a customer." | J9: UNRESOLVED | K9: Deadline and the definition of 'stop being a customer' are missing. Question in ISS-07.
A10: NFR-09 | B10: Security / compliance (contracts) | C10: A data processing agreement shall exist with every cloud or SaaS provider that processes personal data. | D10: Share of such providers with a signed data processing agreement | E10: 100 | F10: % | G10: Contract register check before go-live. | H10: 01_Requirements/sources/01_note_gdpr-consultant_2026-08-20.txt | I10: 01_note_gdpr-consultant_2026-08-20.txt [bullet 4]: "A data processing agreement is needed with any cloud/SaaS provider." | J10: DIRECT | K10: Applies to Vipps, Fiken, hosting and e-mail providers as relevant (INFERRED).
A11: NFR-10 | B11: Usability (localisation) | C11: The user interface shall be available in Norwegian and English. | D11: Supported UI languages | E11: 2 (Norwegian, English) | F11: languages | G11: Review of all customer-facing screens in both languages. | H11: 03_Architecture/03_landscape_current-it_2026-10-20.txt 04_Data/04_dataset_customer-emails_2026-10-20.csv | I11: 03_landscape_current-it_2026-10-20.txt [Constraints]: "Norwegian and English UI." 04_dataset_customer-emails_2026-10-20.csv [E012]: "Is your menu available in English with allergens marked?" | J11: DIRECT | K11: Scope (customer-facing only, or also kitchen and admin views) is unresolved (ISS-19).
A12: NFR-11 | B12: Cost (operational constraint) | C12: Running costs of the solution shall stay below 3 000 NOK per month. | D12: Monthly running cost | E12: < 3 000 | F12: NOK/month | G12: Sum of monthly hosting, licence and SaaS invoices after go-live. | H12: 00_Project_management/00_plan_budget-and-constraints_2026-10-20.txt 03_Architecture/03_landscape_current-it_2026-10-20.txt | I12: 00_plan_budget-and-constraints_2026-10-20.txt [Running cost]: "Running cost target: < 3 000 NOK/month" 03_landscape_current-it_2026-10-20.txt [Constraints]: "prefer low running cost (< 3 000 NOK/month)" | J12: DIRECT | K12: Project constraint rather than a product quality. Whether transaction fees (e.g. Vipps) count is not documented.
... A14: NFR-13 | B14: Compatibility | C14: The kitchen view shall run on a wall-mounted tablet. | D14: Supported kitchen device | E14: TBC (device and OS not specified) | F14: device | G14: Test on the selected device. | H14: 01_Requirements/sources/01_interview_head-chef_2026-08-15.txt 03_Architecture/03_landscape_current-it_2026-10-20.txt | I14: 01_interview_head-chef_2026-08-15.txt [Q1]: "Tablet on the wall." 03_landscape_current-it_2026-10-20.txt [Kitchen]: "one old iPad nobody uses" | J14: INFERRED | K14: Whether the existing iPad should be reused is not stated.

Sheet Conflicts and open questions
A1: Issue ID | B1: Issue Type | C1: Topic | D1: Description | E1: Stakeholder/Source A and Position | F1: Stakeholder/Source B and Position | G1: Source File(s) | H1: Supporting Quote/Evidence | I1: Potential Impact | J1: Specific Product-Owner Question | K1: Decision Owner (if evidenced) | L1: Status
A2: ISS-01 | B2: Conflict | C2: Deposit / prepayment | D2: The owner wants a 30 % deposit on every booking; the event coordinator and the corporate customer say corporate customers cannot or will not prepay. | E2: Owner (01_interview_owner): 30 % deposit for every booking, 'no deposit, no booking'. | F2: Event coordinator and corporate customer: no prepayment for corporate customers; deposit acceptable for weddings. | G2: 01_Requirements/sources/01_interview_owner_2026-08-14.txt 01_Requirements/sources/01_interview_event-coordinator_2026-08-15.txt 01_Requirements/sources/01_interview_corporate-customer_2026-08-19.txt | H2: 01_interview_owner_2026-08-14.txt [Q2]: "I want the system to take a 30 % deposit when someone books - no deposit, no booking." 01_interview_event-coordinator_2026-08-15.txt [Q3]: "If we force a deposit on them, we will lose them. For weddings a deposit makes sense." 01_interview_corporate-customer_2026-08-19.txt [Q3]: "We cannot prepay, our finance department does not allow it." | I2: Affects US-22 and US-23. Risk of losing corporate customers, or of continued no-shows. | J2: Which booking types require the 30 % deposit: (a) all, (b) weddings only, (c) all except corporate customers on monthly invoicing? What are the refund rules? | K2: Ingrid Solheim (product owner, per 00_minutes bullet 5) | L2: Open
A3: ISS-02 | B3: Open Question | C3: Build vs buy | D3: Kick-off left open whether to build a custom system or configure a catering SaaS. | E3: Kick-off minutes: open question. | F3: - | G3: 00_Project_management/00_minutes_kickoff-meeting_2026-08-12.txt | H3: 00_minutes_kickoff-meeting_2026-08-12.txt [bullet 8]: "Open question: build our own system or configure an off-the-shelf catering SaaS?" | I3: Affects architecture, cost (NFR-11), data processing agreements (NFR-09) and all stories. | J3: Will the team build its own system or configure a catering SaaS? By which sprint must this be decided? | K3: Not evidenced | L3: Open
A4: ISS-03 | B4: Open Question | C4: Order change deadline | D4: No company-wide deadline for customer changes exists. One customer wants changes until 10:00 the day before; the vision says 'change orders any time'. | E4: Corporate customer: changes until 10:00 the day before. | F4: Vision draft v0.3: 'book and change orders any time'. | G4: 01_Requirements/sources/01_interview_corporate-customer_2026-08-19.txt 01_Requirements/sources/01_vision_draft-v0.3_2026-10-20.docx | H4: 01_interview_corporate-customer_2026-08-19.txt [Q2]: "change the number of people until 10:00 the day before" 01_vision_draft-v0.3_2026-10-20.docx [para 1]: "book and change orders any time" | I4: Affects US-11 and kitchen planning. | J4: What is the latest time a customer may change guest numbers or allergies, and does it differ for lunches and events? | K4: Ingrid Solheim (product owner, per 00_minutes bullet 5) | L4: Open
A5: ISS-04 | B5: Missing Evidence | C5: Cancellation terms | D5: A customer asks for cancellation terms; none are documented. | E5: Customer e-mail E013: asks for terms. | F5: - | G5: 04_Data/04_dataset_customer-emails_2026-10-20.csv | H5: 04_dataset_customer-emails_2026-10-20.csv [E013]: "What are your cancellation terms?" | I5: US-13 cannot be fully specified. | J5: What are the cancellation deadlines and fees for each booking type? | K5: Ingrid Solheim (product owner, per 00_minutes bullet 5) | L5: Open
A6: ISS-05 | B6: Dependency | C6: Fiken and EHF | D6: Invoice creation, EHF sending and payment-status updates depend on Fiken's API. A customer received a wrong payment reminder. | E6: IT landscape: Fiken has a REST API and supports EHF. | F6: Customer e-mail E030: wrong payment reminder. | G6: 03_Architecture/03_landscape_current-it_2026-10-20.txt 04_Data/04_dataset_customer-emails_2026-10-20.csv | H6: 03_landscape_current-it_2026-10-20.txt [Accounting]: "Fiken (has a REST API; supports EHF invoices)" 04_dataset_customer-emails_2026-10-20.csv [E030]: "We received a payment reminder for an invoice we paid on 2 Sept." | I6: Affects US-23 and US-24. | J6: Can the team get test access to Fiken's API, and should payment status be read back from Fiken into the system? | K6: Ingrid Solheim (product owner, per 00_minutes bullet 5) | L6: Open
A7: ISS-06 | B7: Open Question | C7: Capacity rule | D7: Capacity is described as 'about 400 covers a day, 250 if there is a wedding with a served dinner'. It is unclear whether this is a hard limit or a warning. | E7: Event coordinator: approximate limits. | F7: - | G7: 01_Requirements/sources/01_interview_event-coordinator_2026-08-15.txt | H7: 01_interview_event-coordinator_2026-08-15.txt [Q4]: "Our kitchen can do about 400 covers a day, 250 if there is a wedding with a served dinner." | I7: Affects US-03 and US-10. | J7: Are 400 and 250 covers per day hard limits that block bookings, or warnings to the coordinator? Who may override them? | K7: Ingrid Solheim (product owner, per 00_minutes bullet 5) | L7: Open
A8: ISS-07 | B8: Missing Evidence | C8: Retention and deletion periods | D8: Retention for non-bookkeeping personal data and deadlines for deletion are not stated. | E8: GDPR note: 'shorter retention period' (no value). | F8: Corporate customer: deletion at end of relationship (no deadline). | G8: 01_Requirements/sources/01_note_gdpr-consultant_2026-08-20.txt 01_Requirements/sources/01_interview_corporate-customer_2026-08-19.txt | H8: 01_note_gdpr-consultant_2026-08-20.txt [bullet 2]: "other personal data should have a shorter retention period." 01_interview_corporate-customer_2026-08-19.txt [Q4]: "delete our employees' names when we stop being a customer." | I8: NFR-07 and NFR-08 cannot be tested; affects US-31. | J8: What retention period applies to personal data not needed for bookkeeping, and within how many days must data be deleted after a request or end of relationship? | K8: Not evidenced | L8: Open
A9: ISS-08 | B9: Open Question | C9: Approval threshold | D9: One customer wants approval above 15 000 NOK. It is unclear whether thresholds are per customer and configurable. | E9: Corporate customer: only the office manager approves orders above 15 000 NOK. | F9: - | G9: 01_Requirements/sources/01_interview_corporate-customer_2026-08-19.txt | H9: 01_interview_corporate-customer_2026-08-19.txt [Q2]: "only I should approve anything above 15 000 NOK." | I9: Affects US-26. | J9: Should approval thresholds be configurable per company account, and is the amount incl. or excl. VAT? | K9: Ingrid Solheim (product owner, per 00_minutes bullet 5) | L9: Open
A10: ISS-09 | B10: Dependency | C10: Vipps integration | D10: Vipps payments depend on an agreement and API access that are not documented. | E10: Kick-off: must integrate with Vipps. | F10: - | G10: 00_Project_management/00_minutes_kickoff-meeting_2026-08-12.txt | H10: 00_minutes_kickoff-meeting_2026-08-12.txt [bullet 2]: "Must integrate with Fiken (accounting) and Vipps (payments)." | I10: Affects US-21 and US-22. | J10: Does Ekte Mat have a Vipps merchant agreement that allows API integration, and who will request test access? | K10: Ingrid Solheim (product owner, per 00_minutes bullet 5) | L10: Open
A11: ISS-10 | B11: Missing Evidence | C11: Performance target | D11: Speed is a stated need, but no target is given. | E11: Head chef: 'do not make it slow'. | F11: - | G11: 01_Requirements/sources/01_interview_head-chef_2026-08-15.txt | H11: 01_interview_head-chef_2026-08-15.txt [Q4]: "Please do not make it slow." | I11: NFR-01 cannot be tested. | J11: What is the maximum acceptable page load time, on which device and network? | K11: Ingrid Solheim (product owner, per 00_minutes bullet 5) | L11: Open
A12: ISS-11 | B12: Missing Evidence | C12: Availability target | D12: 'At any hour' has no numeric availability target. | E12: Owner: booking at any hour. | F12: - | G12: 01_Requirements/sources/01_interview_owner_2026-08-14.txt | H12: 01_interview_owner_2026-08-14.txt [Q2]: "at any hour." | I12: NFR-02 cannot be tested; affects hosting choice and cost. | J12: What monthly availability (%) is required for menus and booking, and are planned maintenance windows acceptable? | K12: Ingrid Solheim (product owner, per 00_minutes bullet 5) | L12: Open
... A25: ISS-24 | B25: Missing Evidence | C25: GDPR advice verification | D25: GDPR obligations come from a phone note, not a written legal assessment. | E25: GDPR note header: phone call. | F25: - | G25: 01_Requirements/sources/01_note_gdpr-consultant_2026-08-20.txt | H25: 01_note_gdpr-consultant_2026-08-20.txt [header]: "Note from data-protection consultant (phone call, 20 Aug 2026)" | I25: Risk of building on unverified legal assumptions (NFR-04 to NFR-09). | J25: Can the consultant confirm the advice in writing, including the 5-year bookkeeping retention? | K25: Not evidenced | L25: Open
A28: AUDIT TRAIL (separate from the issue table above)
A29: Inspected 2026-10-22. Story counts are live formulas over the 'User stories' Source File(s) column.
A30: # | B30: File | C30: Relative Path (from EkteMat_repo) | D30: File Type | E30: Read Successfully | F30: Contributed Stories | G30: Distinct Stories Supported | H30: Other Contribution | I30: Notes / Exclusion Reason
A31: 1 | B31: 01_interview_owner_2026-08-14.txt | C31: 01_Requirements/sources/01_interview_owner_2026-08-14.txt | D31: txt | E31: Yes | F31: =IF(G31>0,"Yes","No") -> Yes | G31: =COUNTIF('User stories'!$H$2:$H$32,"*"&B31&"*") -> 7 | H31: Stakeholders, NFR-02, issues
A32: 2 | B32: 01_interview_event-coordinator_2026-08-15.txt | C32: 01_Requirements/sources/01_interview_event-coordinator_2026-08-15.txt | D32: txt | E32: Yes | F32: =IF(G32>0,"Yes","No") -> Yes | G32: =COUNTIF('User stories'!$H$2:$H$32,"*"&B32&"*") -> 7 | H32: Stakeholders, issues
A33: 3 | B33: 01_interview_head-chef_2026-08-15.txt | C33: 01_Requirements/sources/01_interview_head-chef_2026-08-15.txt | D33: txt | E33: Yes | F33: =IF(G33>0,"Yes","No") -> Yes | G33: =COUNTIF('User stories'!$H$2:$H$32,"*"&B33&"*") -> 5 | H33: NFR-01, 03, 12, 13; issues
A34: 4 | B34: 01_interview_corporate-customer_2026-08-19.txt | C34: 01_Requirements/sources/01_interview_corporate-customer_2026-08-19.txt | D34: txt | E34: Yes | F34: =IF(G34>0,"Yes","No") -> Yes | G34: =COUNTIF('User stories'!$H$2:$H$32,"*"&B34&"*") -> 9 | H34: NFR-04, 08; issues
A35: 5 | B35: 01_note_gdpr-consultant_2026-08-20.txt | C35: 01_Requirements/sources/01_note_gdpr-consultant_2026-08-20.txt | D35: txt | E35: Yes | F35: =IF(G35>0,"Yes","No") -> Yes | G35: =COUNTIF('User stories'!$H$2:$H$32,"*"&B35&"*") -> 3 | H35: NFR-05 to 09; issues | I35: Advice from a phone note; not legally verified.
A36: 6 | B36: 01_vision_draft-v0.3_2026-10-20.docx | C36: 01_Requirements/sources/01_vision_draft-v0.3_2026-10-20.docx | D36: docx | E36: Yes | F36: =IF(G36>0,"Yes","No") -> Yes | G36: =COUNTIF('User stories'!$H$2:$H$32,"*"&B36&"*") -> 4 | H36: Issues | I36: Text read from paragraphs; no tables or images found.
A37: 7 | B37: 00_minutes_kickoff-meeting_2026-08-12.txt | C37: 00_Project_management/00_minutes_kickoff-meeting_2026-08-12.txt | D37: txt | E37: Yes | F37: =IF(G37>0,"Yes","No") -> Yes | G37: =COUNTIF('User stories'!$H$2:$H$32,"*"&B37&"*") -> 3 | H37: Stakeholders, issues | I37: Expected input; located in 00_Project_management, not in sources/.
A38: 8 | B38: 00_plan_budget-and-constraints_2026-10-20.txt | C38: 00_Project_management/00_plan_budget-and-constraints_2026-10-20.txt | D38: txt | E38: Yes | F38: =IF(G38>0,"Yes","No") -> No | G38: =COUNTIF('User stories'!$H$2:$H$32,"*"&B38&"*") -> 0 | H38: NFR-11, issues | I38: Expected input; located in 00_Project_management. No functional stories: content is constraints only.
A39: 9 | B39: 02_process_as-is-order-handling_2026-08-15.md | C39: 02_Analysis_and_models/02_process_as-is-order-handling_2026-08-15.md | D39: md | E39: Yes | F39: =IF(G39>0,"Yes","No") -> Yes | G39: =COUNTIF('User stories'!$H$2:$H$32,"*"&B39&"*") -> 8 | H39: Stakeholders, issues | I39: Expected input; located in 02_Analysis_and_models.
A40: 10 | B40: 03_landscape_current-it_2026-10-20.txt | C40: 03_Architecture/03_landscape_current-it_2026-10-20.txt | D40: txt | E40: Yes | F40: =IF(G40>0,"Yes","No") -> Yes | G40: =COUNTIF('User stories'!$H$2:$H$32,"*"&B40&"*") -> 2 | H40: NFR-04, 10-13; issues | I40: Expected input; located in 03_Architecture.
A41: 11 | B41: 04_dataset_customer-emails_2026-10-20.csv | C41: 04_Data/04_dataset_customer-emails_2026-10-20.csv | D41: csv | E41: Yes | F41: =IF(G41>0,"Yes","No") -> Yes | G41: =COUNTIF('User stories'!$H$2:$H$32,"*"&B41&"*") -> 21 | H41: Stakeholders, NFR-10, issues | I41: Expected input; located in 04_Data. 30 records; columns email_id, received, from_name, from_address, subject, body, language. Cited by email_id; names and addresses not reproduced. Records used: see note below.
A42: 12 | B42: 04_reference_lunch-menu-autumn_2026-10-20.txt | C42: 04_Data/04_reference_lunch-menu-autumn_2026-10-20.txt | D42: txt | E42: Yes | F42: =IF(G42>0,"Yes","No") -> Yes | G42: =COUNTIF('User stories'!$H$2:$H$32,"*"&B42&"*") -> 1 | H42: - | I42: Reference material (allergen list). Not in the expected-input list; included because it supports US-06.
A43: 13 | B43: 04_dataset_orders-2024-2025_2026-09-27.xlsx | C43: 04_Data/04_dataset_orders-2024-2025_2026-09-27.xlsx | D43: xlsx | E43: Partially (headers only) | F43: =IF(G43>0,"Yes","No") -> No | G43: =COUNTIF('User stories'!$H$2:$H$32,"*"&B43&"*") -> 0 | H43: - | I43: Historical order data; not a requirements source in the brief. Not analysed for stories.
A44: 14 | B44: 02_benchmark_competitor-links_2026-10-20.txt | C44: 02_Analysis_and_models/02_benchmark_competitor-links_2026-10-20.txt | D44: txt | E44: Yes | F44: =IF(G44>0,"Yes","No") -> No | G44: =COUNTIF('User stories'!$H$2:$H$32,"*"&B44&"*") -> 0 | H44: - | I44: Excluded: competitor links for benchmarking only; external sites not opened (no research authorised).
A45: 15 | B45: 00_todo_sprint0-setup_2026-10-20.txt | C45: 00_Project_management/00_todo_sprint0-setup_2026-10-20.txt | D45: txt | E45: Yes | F45: =IF(G45>0,"Yes","No") -> No | G45: =COUNTIF('User stories'!$H$2:$H$32,"*"&B45&"*") -> 0 | H45: - | I45: Excluded: team to-do, no requirements content.
A46: 16 | B46: 99_note_logo-ideas_2026-10-20.txt | C46: 99_Not_relevant/99_note_logo-ideas_2026-10-20.txt | D46: txt | E46: Yes | F46: =IF(G46>0,"Yes","No") -> No | G46: =COUNTIF('User stories'!$H$2:$H$32,"*"&B46&"*") -> 0 | H46: - | I46: Excluded: marked not relevant to system development.
A47: 17 | B47: README.md | C47: README.md | D47: md | E47: Yes | F47: =IF(G47>0,"Yes","No") -> No | G47: =COUNTIF('User stories'!$H$2:$H$32,"*"&B47&"*") -> 0 | H47: - | I47: Excluded: repository index written by the team.
B49: Total unique user stories | G49: =COUNTA('User stories'!$A$2:$A$32) -> 31
B50: Sum of per-file story counts | G50: =SUM(G31:G47) -> 70
B51: Note | C51: The sum exceeds the unique total because one story can be supported by several files. CSV records supporting stories: E001, E002, E003, E004, E005, E006, E007, E008, E009, E010, E011, E012, E013, E014, E015, E016, E017, E018, E019, E021, E022, E023, E024, E028, E029. Records used only for stakeholders/NFRs/issues: E020, E025, E027, E030. Records with no requirement content (not used): E026. No story is classified Won't: no source explicitly excludes or defers a need. Originals in EkteMat_project_inbox were not re-read; the repo copies are SHA-256-identical (verified 2026-10-22). The inbox file 'Kopi av interview Sunniva (2).txt' is an exact duplicate of the event-coordinator interview and was not counted.
